coloration/__init__.py
coloration/__meta__.py
coloration/_init.py
coloration/_stream.py
coloration/_utils.py
coloration/_ansi/__init__.py
coloration/_ansi/_codes.py
coloration/_ansi/_codes_flat.py
coloration/_ansi/_constants.py
coloration/_ansi/_utils.py
coloration/_highlighting/__init__.py
coloration/_highlighting/_default.py
coloration/_highlighting/_highlighter.py
coloration/_highlighting/_regex.py
coloration/_highlighting/_repl.py
coloration/_highlighting/_span.py
coloration/_highlighting/_utils.py
coloration/logging/__init__.py
coloration/logging/_formatter.py
coloration/logging/_handler.py
coloration/logging/_logging.py
coloration-0.1.1.dist-info/LICENSE.txt
coloration-0.1.1.dist-info/METADATA
coloration-0.1.1.dist-info/WHEEL
coloration-0.1.1.dist-info/top_level.txt
coloration-0.1.1.dist-info/zip-safe
coloration-0.1.1.dist-info/RECORD
