Metadata-Version: 2.1
Name: coloration
Version: 0.1.1
Summary: Python library for terminal and logs coloring and styling
Home-page: https://github.com/polyvertex/coloration
Author: Jean-Charles Lefebvre
Author-email: polyvertex@gmail.com
License: MIT
Project-URL: Source Code, https://github.com/polyvertex/coloration
Project-URL: Issue Tracker, https://github.com/polyvertex/coloration/issues
Keywords: terminal,coloring,styling,logging
Classifier: Development Status :: 4 - Beta
Classifier: License :: OSI Approved :: MIT License
Classifier: Operating System :: OS Independent
Classifier: Programming Language :: Python
Classifier: Programming Language :: Python :: 3.8
Classifier: Programming Language :: Python :: 3.9
Classifier: Programming Language :: Python :: 3.10
Classifier: Programming Language :: Python :: 3.11
Requires-Python: >=3.8
License-File: LICENSE.txt
Provides-Extra: dev
Requires-Dist: flake8 ; extra == 'dev'
Requires-Dist: pycodestyle ; extra == 'dev'
Requires-Dist: pyflakes ; extra == 'dev'
Requires-Dist: mccabe ; extra == 'dev'
Requires-Dist: flake8-bugbear ; extra == 'dev'
Requires-Dist: flake8-noqa ; extra == 'dev'
Requires-Dist: dlint ; extra == 'dev'
Requires-Dist: pylint ; extra == 'dev'
Requires-Dist: check-manifest (>=0.48) ; extra == 'dev'
Requires-Dist: readme-renderer (>=33.0) ; extra == 'dev'
Requires-Dist: build ; extra == 'dev'
Requires-Dist: twine ; extra == 'dev'
